serpent_web-0.3.2.dist-info/METADATA
serpent_web-0.3.2.dist-info/WHEEL
serpent_web-0.3.2.dist-info/entry_points.txt
serpent_web/__init__.py
serpent_web/azure/__init__.py
serpent_web/azure/azure_service_identity.py
serpent_web/azure/managed_identity.py
serpent_web/core/__init__.py
serpent_web/core/authentication/__init__.py
serpent_web/core/authentication/oauth20/__init__.py
serpent_web/core/authentication/oauth20/settings.py
serpent_web/core/authentication/oauth20/token_util.py
serpent_web/core/util/__init__.py
serpent_web/core/util/datetime_helpers.py
serpent_web/core/util/string_helpers.py
serpent_web/data/__init__.py
serpent_web/data/cosmos/__init__.py
serpent_web/data/cosmos/cosmos_client_context.py
serpent_web/data/cosmos/cosmos_settings.py
serpent_web/data/data_schemas.py
serpent_web/data/sql/__init__.py
serpent_web/data/sql/base_schema.py
serpent_web/data/sql/base_sql_model.py
serpent_web/data/sql/base_sql_repository.py
serpent_web/data/sql/base_sqlite_model.py
serpent_web/data/sql/databricks/__init__.py
serpent_web/data/sql/databricks/base_databricks_sql_model.py
serpent_web/data/sql/databricks/base_databricks_sql_repository.py
serpent_web/data/sql/pydantic_helpers.py
serpent_web/data/sql/sql_alchemy_helpers.py
serpent_web/data/sql/sql_context.py
serpent_web/data/sql/sql_database_type.py
serpent_web/domain/__init__.py
serpent_web/domain/base_manager.py
serpent_web/domain/base_sql_manager.py
serpent_web-0.3.2.dist-info/RECORD
