Metadata-Version: 2.1
Name: serpent-web
Version: 0.3.2
Summary: Core, Data, and Utility libraries for api development
Author-Email: Brian Aiken <bpaiken570@gmail.com>
License: MIT
Requires-Python: <3.12,>=3.10
Requires-Dist: cachetools>=5.4.0
Requires-Dist: python-jose>=3.3.0
Requires-Dist: starlette>=0.37.0
Requires-Dist: requests>=2.32.3
Requires-Dist: jsonpath-ng>=1.6.1
Requires-Dist: pydantic>=2.8.2
Requires-Dist: xxhash>=3.4.1
Requires-Dist: pydantic-settings>=2.4.0
Requires-Dist: sqlalchemy>=2.0.32
